beancount_categorizers/__init__.py
beancount_categorizers/categorizer.py
beancount_categorizers/flag_txn.py
beancount_categorizers/hooks.py
beancount_categorizers-0.2.0.dist-info/WHEEL
beancount_categorizers-0.2.0.dist-info/METADATA
beancount_categorizers-0.2.0.dist-info/RECORD
